<?xml version='1.0' encoding='UTF-8'?>
<types:mule xmlns:types="http://www.mulesoft.org/schema/mule/types">
  <types:catalog>
    <types:type name="auto_c5c37c70-db9a-4b9b-a8be-ae69f1308b66_Input-Payload" format="java">
      <types:shape format="raml" autogeneratedOrigin="49a23688-8e79-44d4-a3e5-2bfa417948d7"><![CDATA[#%RAML 1.0 DataType
type: string]]></types:shape>
    </types:type>
    <types:type name="auto_c5c37c70-db9a-4b9b-a8be-ae69f1308b66_Input-Attributes" format="java">
      <types:shape format="weave" example="weave/autogenerated/c5c37c70-db9a-4b9b-a8be-ae69f1308b66/Input-Attributes.wev" autogeneratedOrigin="49a23688-8e79-44d4-a3e5-2bfa417948d7"><![CDATA[%dw 2.0

type auto_c5c37c70_db9a_4b9b_a8be_ae69f1308b66_Input_Attributes = {|
  listenerPath: String, 
  rawRequestPath: String, 
  relativePath: String, 
  maskedRequestPath: String, 
  version: String, 
  scheme: String, 
  method: String, 
  requestUri: String, 
  rawRequestUri: String, 
  queryString: String, 
  localAddress: String, 
  remoteAddress: String, 
  clientCertificate?: java_security_cert_Certificate, 
  queryParams: { _?: String }, 
  uriParams: { _?: String }, 
  requestPath: String, 
  headers: { _?: String }
|} {"typeAlias": "HttpRequestAttributes",
"typeId": "org.mule.extension.http.api.HttpRequestAttributes"}
type java_security_cert_Certificate = {|
  encoded?: Binary, 
  publicKey?: java_security_PublicKey, 
  "type"?: String
|} {"typeAlias": "Certificate",
"typeId": "java.security.cert.Certificate"}
type java_security_PublicKey = {|  |} {"typeAlias": "PublicKey",
"typeId": "java.security.PublicKey"}





]]></types:shape>
    </types:type>
    <types:type name="auto_c5c37c70-db9a-4b9b-a8be-ae69f1308b66_Output-Payload" format="java">
      <types:shape format="raml" autogeneratedOrigin="49a23688-8e79-44d4-a3e5-2bfa417948d7"><![CDATA[#%RAML 1.0 DataType
type: string]]></types:shape>
    </types:type>
    <types:type name="auto_c5c37c70-db9a-4b9b-a8be-ae69f1308b66_Output-Attributes" format="java">
      <types:shape format="weave" example="weave/autogenerated/c5c37c70-db9a-4b9b-a8be-ae69f1308b66/Output-Attributes.wev" autogeneratedOrigin="49a23688-8e79-44d4-a3e5-2bfa417948d7"><![CDATA[%dw 2.0

type auto_c5c37c70_db9a_4b9b_a8be_ae69f1308b66_Output_Attributes = {|
  listenerPath: String, 
  rawRequestPath: String, 
  relativePath: String, 
  maskedRequestPath: String, 
  version: String, 
  scheme: String, 
  method: String, 
  requestUri: String, 
  rawRequestUri: String, 
  queryString: String, 
  localAddress: String, 
  remoteAddress: String, 
  clientCertificate?: java_security_cert_Certificate, 
  queryParams: { _?: String }, 
  uriParams: { _?: String }, 
  requestPath: String, 
  headers: { _?: String }
|} {"typeAlias": "HttpRequestAttributes",
"typeId": "org.mule.extension.http.api.HttpRequestAttributes"}
type java_security_cert_Certificate = {|
  encoded?: Binary, 
  publicKey?: java_security_PublicKey, 
  "type"?: String
|} {"typeAlias": "Certificate",
"typeId": "java.security.cert.Certificate"}
type java_security_PublicKey = {|  |} {"typeAlias": "PublicKey",
"typeId": "java.security.PublicKey"}





]]></types:shape>
    </types:type>
    <types:type name="auto_aa677d93-9204-41da-849e-47c0eea52f1a_Input-Variables-httpStatus" format="java">
      <types:shape format="raml" autogeneratedOrigin="b3fce3a1-5a7f-4e22-a82c-74a4da398c65"><![CDATA[#%RAML 1.0 DataType
type: string]]></types:shape>
    </types:type>
    <types:type name="auto_aa677d93-9204-41da-849e-47c0eea52f1a_Output-Payload" format="json">
      <types:shape format="weave" example="weave/autogenerated/aa677d93-9204-41da-849e-47c0eea52f1a/Output-Payload.wev" autogeneratedOrigin="b3fce3a1-5a7f-4e22-a82c-74a4da398c65"><![CDATA[%dw 2.0

type auto_aa677d93_9204_41da_849e_47c0eea52f1a_Output_Payload = {|
  errorStatusCode: Null, 
  errorMessage: String | Null, 
  errorType: String | Null
|}

]]></types:shape>
    </types:type>
    <types:type name="auto_aa677d93-9204-41da-849e-47c0eea52f1a_Output-Variables-httpStatus" format="java">
      <types:shape format="raml" autogeneratedOrigin="b3fce3a1-5a7f-4e22-a82c-74a4da398c65"><![CDATA[#%RAML 1.0 DataType
type: string]]></types:shape>
    </types:type>
  </types:catalog>
  <types:enrichment select="#c5c37c70-db9a-4b9b-a8be-ae69f1308b66">
    <types:processor-declaration>
      <types:input-event>
        <types:message>
          <types:payload type="auto_c5c37c70-db9a-4b9b-a8be-ae69f1308b66_Input-Payload"/>
          <types:attributes type="auto_c5c37c70-db9a-4b9b-a8be-ae69f1308b66_Input-Attributes"/>
        </types:message>
      </types:input-event>
      <types:output-event>
        <types:message>
          <types:payload type="auto_c5c37c70-db9a-4b9b-a8be-ae69f1308b66_Output-Payload"/>
          <types:attributes type="auto_c5c37c70-db9a-4b9b-a8be-ae69f1308b66_Output-Attributes"/>
        </types:message>
      </types:output-event>
    </types:processor-declaration>
  </types:enrichment>
  <types:enrichment select="#aa677d93-9204-41da-849e-47c0eea52f1a">
    <types:processor-declaration>
      <types:input-event>
        <types:variables>
          <types:variable name="httpStatus" type="auto_aa677d93-9204-41da-849e-47c0eea52f1a_Input-Variables-httpStatus"/>
        </types:variables>
      </types:input-event>
      <types:output-event>
        <types:message>
          <types:payload type="auto_aa677d93-9204-41da-849e-47c0eea52f1a_Output-Payload"/>
        </types:message>
        <types:variables>
          <types:variable name="httpStatus" type="auto_aa677d93-9204-41da-849e-47c0eea52f1a_Output-Variables-httpStatus"/>
        </types:variables>
      </types:output-event>
    </types:processor-declaration>
  </types:enrichment>
</types:mule>